pypomes_ldap/__init__.py
pypomes_ldap/ldap_pomes.py
pypomes_ldap-0.2.2.dist-info/METADATA
pypomes_ldap-0.2.2.dist-info/WHEEL
pypomes_ldap-0.2.2.dist-info/licenses/LICENSE
pypomes_ldap-0.2.2.dist-info/RECORD
