Metadata-Version: 2.4
Name: pypomes_ldap
Version: 0.2.2
Summary: A collection of Python pomes, penyeach (LDAP module)
Project-URL: Homepage, https://github.com/TheWiseCoder/PyPomes-LDAP
Project-URL: Bug Tracker, https://github.com/TheWiseCoder/PyPomes-LDAP/issues
Author-email: GT Nunes <wisecoder01@gmail.com>
License-File: LICENSE
Classifier: License :: OSI Approved :: MIT License
Classifier: Operating System :: OS Independent
Classifier: Programming Language :: Python :: 3
Requires-Python: >=3.14
Requires-Dist: pypomes-core>=2.9.4
Requires-Dist: python-ldap>=3.4.5
